{"algorithm_index.md":"e89cc3de","book_index.md":"72f28f20","front_element-plus_switch.md":"cc9dffec","front_engineer_taro.md":"49d3dfe3","front_js_call.md":"8144924d","front_js_extends.md":"d9b06730","front_js_instanceof.md":"de817d5b","front_js_module.md":"5db51a1d","front_js_new.md":"82d3feb2","front_js_this.md":"394a1fcb","front_js_varletconst.md":"c5c2ddab","front_network_http.md":"bc0a13db","front_network_tcp-udp.md":"f297ce65","front_node_koa-onion-model.md":"3b244d8e","front_node_resolve.md":"851d0f2e","front_project_dynamic-router.md":"0fbc5c08","front_project_select-test.md":"30a73d1a","front_vue-use_useaxios.md":"afaca526","front_vue-use_usedark.md":"c078f7d5","front_vue_computed.md":"18a9b520","front_vue_reactive.md":"68719a87","front_vue_set.md":"ce7db6d6","front_vue_vue3-advance.md":"5f5a9243","front_vue_vuexmount.md":"96dca34e","front_vue_watch.md":"196be46f","index.md":"2b878484","me_index.md":"f2d82a8b"}
