{"algorithm_index.md":"e89cc3de","book_index.md":"72f28f20","front_element-plus_switch.md":"19089467","front_engineer_taro.md":"49d3dfe3","front_js_call.md":"8144924d","front_js_extends.md":"ff03fdcc","front_js_instanceof.md":"de817d5b","front_js_module.md":"554bb1f6","front_js_new.md":"82d3feb2","front_js_this.md":"97292f8f","front_js_varletconst.md":"c5c2ddab","front_network_http.md":"4de5968d","front_network_tcp-udp.md":"f297ce65","front_node_koa-onion-model.md":"833d057c","front_node_resolve.md":"bd34de81","front_project_dynamic-router.md":"0fbc5c08","front_project_select-test.md":"30a73d1a","front_vue-use_useaxios.md":"afaca526","front_vue-use_usedark.md":"c078f7d5","front_vue_computed.md":"ccf11e75","front_vue_reactive.md":"45d476a5","front_vue_set.md":"f78c149a","front_vue_vue3-advance.md":"2c1d02ef","front_vue_vuexmount.md":"1a0c41ee","front_vue_watch.md":"3f6583fb","index.md":"2b878484","me_index.md":"ddcdcf85"}
